peds/__init__.py
peds/family.py
peds/ped.py
peds/person.py
peds/utils.py
peds-1.3.2.dist-info/DESCRIPTION.rst
peds-1.3.2.dist-info/METADATA
peds-1.3.2.dist-info/RECORD
peds-1.3.2.dist-info/WHEEL
peds-1.3.2.dist-info/metadata.json
peds-1.3.2.dist-info/top_level.txt
