Metadata-Version: 2.0
Name: peds
Version: 1.3.2
Summary: Package for parsing pedigree files
Home-page: https://github.com/jeremymcrae/peds
Author: Jeremy McRae
Author-email: jmcrae@illumina.com
License: MIT
Platform: UNKNOWN
Classifier: Development Status :: 3 - Alpha
Classifier: Topic :: Scientific/Engineering :: Bio-Informatics
Requires-Dist: networkx
